nui/__init__.py
nui/cui/__init__.py
nui/cui/v1/__init__.py
nui/cui/v1/return_code.py
nui/cui/v1/shell.py
nui/cui/v2/__init__.py
nui/cui/v2/api.py
nui/cui/v2/com.py
nui/cui/v2/consts.py
nui/cui/v2/retcom.py
nui/cui/v2/shell.py
nui/cui/v3/__init__.py
nui/cui/v3/api.py
nui/cui/v3/com.py
nui/cui/v3/consts.py
nui/cui/v3/retcom.py
nui/cui/v3/shell.py
nui/gui/__init__.py
nui/gui/v2/__init__.py
nui/gui/v2/stage.py
nui/gui/v2/style.py
nui/gui/v2/validator.py
nui/gui/v2/widgets/__init__.py
nui/gui/v2/widgets/arch.py
nui/gui/v2/widgets/basic.py
nui/gui/v2/widgets/button_groups.py
nui/gui/v2/widgets/date.py
nui/gui/v2/widgets/flat_button.py
nui/gui/v2/widgets/form.py
nui/gui/v2/widgets/imethods.py
nui/gui/v2/widgets/search.py
nui/gui/v2/widgets/single_listbox.py
nui/gui/v2/widgets/toggle.py
nui/gui/v2/widgets/twin_listbox.py
nui-1.1.dist-info/LICENSE
nui-1.1.dist-info/METADATA
nui-1.1.dist-info/WHEEL
nui-1.1.dist-info/top_level.txt
nui-1.1.dist-info/RECORD
