Metadata-Version: 2.1
Name: nui
Version: 1.1
Summary: Small gui/cui framework
Home-page: https://github.com/TheNovi/Nui
Author: TheNovi
Author-email: jakub.novi.novacek@gmail.com
License: UNKNOWN
Platform: UNKNOWN
Classifier: Development Status :: 4 - Beta
Classifier: Intended Audience :: Developers
Classifier: License :: OSI Approved :: MIT License
Classifier: Programming Language :: Python :: 3.9
Requires-Python: >=3.9
